jwthenticator/__init__.py
jwthenticator/api.py
jwthenticator/client.py
jwthenticator/consts.py
jwthenticator/exceptions.py
jwthenticator/keys.py
jwthenticator/loop_management.py
jwthenticator/models.py
jwthenticator/schemas.py
jwthenticator/server.py
jwthenticator/server_utils.py
jwthenticator/tokens.py
jwthenticator/utils.py
jwthenticator-1.6.3.dist-info/LICENSE
jwthenticator-1.6.3.dist-info/METADATA
jwthenticator-1.6.3.dist-info/WHEEL
jwthenticator-1.6.3.dist-info/RECORD
