Metadata-Version: 2.1
Name: jwthenticator
Version: 1.6.3
Summary: A cloud first service for key to JWT authentication library and server written in Python 3.
Home-page: https://github.com/claroty/jwthenticator
License: Apache-2.0
Author: Guy Zylberberg
Author-email: guyzyl@gmail.com
Requires-Python: >=3.9,<4.0
Classifier: License :: OSI Approved :: Apache Software License
Classifier: Programming Language :: Python :: 3
Classifier: Programming Language :: Python :: 3.9
Classifier: Programming Language :: Python :: 3.10
Classifier: Programming Language :: Python :: 3.11
Classifier: Programming Language :: Python :: 3.12
Classifier: Programming Language :: Python :: 3.13
Requires-Dist: aiohttp (>=3.9.5,<4.0.0)
Requires-Dist: aiosqlite (>=0.20.0,<0.21.0)
Requires-Dist: asyncpg (>=0.28.0,<0.29.0) ; platform_python_implementation == "CPython"
Requires-Dist: cryptography (>=41.0.3,<=43.0.4)
Requires-Dist: environs (>=9.3.1,<10.0.0)
Requires-Dist: marshmallow (>=3.9,<4.0)
Requires-Dist: marshmallow-dataclass (>=8.3,<9.0)
Requires-Dist: pg8000 (==1.16.6)
Requires-Dist: pycryptodomex (>=3.9,<4.0)
Requires-Dist: pyjwt (>=1.7,<3.0.0)
Requires-Dist: sqlalchemy (>=2.0,<2.1.0)
Requires-Dist: sqlalchemy-utils (>=0.33.0,<1.0.0)
Project-URL: Documentation, https://github.com/claroty/jwthenticator
